copyrightify/__init__.py
copyrightify/config.yaml
copyrightify/copyrightify.py
copyrightify-0.0.3.dist-info/DESCRIPTION.rst
copyrightify-0.0.3.dist-info/METADATA
copyrightify-0.0.3.dist-info/RECORD
copyrightify-0.0.3.dist-info/WHEEL
copyrightify-0.0.3.dist-info/entry_points.txt
copyrightify-0.0.3.dist-info/metadata.json
copyrightify-0.0.3.dist-info/top_level.txt
