Metadata-Version: 2.0
Name: copyrightify
Version: 0.0.3
Summary: Apply copyright/license headers to source files
Home-page: https://github.com/locusrobotics/copyrightify
Author: Paul Bovbel
Author-email: pbovbel@locusrobotics.com
License: BSD
Platform: UNKNOWN
Classifier: Environment :: Console
Classifier: Intended Audience :: Developers
Classifier: Operating System :: POSIX
Classifier: Programming Language :: Python
Classifier: Topic :: Software Development :: Documentation
Requires-Dist: GitPython (>=2.1)
Requires-Dist: Jinja2 (>=2.9)
Requires-Dist: PyYaml (>=3.12)
